jupyterlab_forum/__init__.py
jupyterlab_forum/_version.py
jupyterlab_forum-0.1.25.data/data/share/jupyter/labextensions/jupyterlab_forum/package.json
jupyterlab_forum-0.1.25.data/data/share/jupyter/labextensions/jupyterlab_forum/static/131.c9c66a3cce8b179ea435.js
jupyterlab_forum-0.1.25.data/data/share/jupyter/labextensions/jupyterlab_forum/static/361.53939b3943da62c086f2.js
jupyterlab_forum-0.1.25.data/data/share/jupyter/labextensions/jupyterlab_forum/static/539.a0f502d2230713490e9d.js
jupyterlab_forum-0.1.25.data/data/share/jupyter/labextensions/jupyterlab_forum/static/728.0bd151e6899b2729d5a9.js
jupyterlab_forum-0.1.25.data/data/share/jupyter/labextensions/jupyterlab_forum/static/remoteEntry.86962dbc02d07bb55fca.js
jupyterlab_forum-0.1.25.data/data/share/jupyter/labextensions/jupyterlab_forum/static/style.js
jupyterlab_forum-0.1.25.data/data/share/jupyter/labextensions/jupyterlab_forum/static/third-party-licenses.json
jupyterlab_forum-0.1.25.data/data/share/jupyter/labextensions/jupyterlab_forum/install.json
jupyterlab_forum-0.1.25.dist-info/METADATA
jupyterlab_forum-0.1.25.dist-info/WHEEL
jupyterlab_forum-0.1.25.dist-info/licenses/LICENSE
jupyterlab_forum-0.1.25.dist-info/RECORD
